pypely/__init__.py
pypely/_types.py
pypely/helpers.py
pypely/core/__init__.py
pypely/core/_debug_helpers.py
pypely/core/functions.py
pypely/core/errors/__init__.py
pypely/core/errors/_formating.py
pypely/core/errors/merge.py
pypely/core/errors/pipeline.py
pypely/memory/__init__.py
pypely/memory/_context.py
pypely/memory/_impl.py
pypely/memory/errors.py
pypely/memory/wrappers.py
pypely-0.2.2.dist-info/LICENSE
pypely-0.2.2.dist-info/METADATA
pypely-0.2.2.dist-info/WHEEL
pypely-0.2.2.dist-info/top_level.txt
pypely-0.2.2.dist-info/RECORD
