Metadata-Version: 2.1
Name: pypely
Version: 0.2.2
Summary: Make data processing easy
Home-page: https://github.com/stoney95/pypely
Author: Stoney95
Author-email: simon@steinheber.info
License: GPLv3.0
Platform: UNKNOWN
Classifier: Programming Language :: Python :: 3
Classifier: License :: OSI Approved :: MIT License
Classifier: Operating System :: OS Independent
Requires-Python: >=3.7
License-File: LICENSE
Provides-Extra: dev
